Workbook

Sheet TATA FINANCE
A1: Finance ID | B1: Model ID | C1: Year | D1: Country | E1: Units Sold | F1: Total Revenue | G1: Profit | H1: Profit Margin (%) | I1: Tax Rate (%) | J1: Marketing Expense (USD) | K1: R&D Expense (USD) | L1: Net Revenue (USD) | M1: Gross Margin (USD) | N1: Operating Expense (USD) | O1: EBITDA (USD) | P1: EBIT (USD) | Q1: Interest Expense (USD) | R1: Tax Paid (USD) | S1: Net Profit (USD) | T1: Cash Flow (USD) | U1: Capital Expenditure (USD) | V1: Depreciation (USD) | W1: Amortization (USD) | X1: Dividend (USD) | Y1: Shares Outstanding
A2: 58 | B2: 1 | C2: 2022 | D2: Australia | E2: 4430 | F2: 43311495 | G2: 5167061.3 | H2: 11.93 | I2: 17.35 | J2: 14019.41 | K2: 18714.17 | L2: 43238958 | M2: 43285764 | N2: 72537.18 | O2: 43242818 | P2: 43238633 | Q2: 4184.64 | R2: 7514544.3 | S2: -2347483 | T2: 75445.59 | U2: 34195.06 | V2: 3199.66 | W2: 660.36 | X2: 3968.45 | Y2: 3128897
A3: 128 | B3: 2 | C3: 2022 | D3: Australia | E3: 2223 | F3: 47693924 | G3: 11079298 | H3: 23.23 | I3: 15.76 | J3: 8007.36 | K3: 10914.76 | L3: 47617422 | M3: 47684894 | N3: 76501.93 | O3: 47621256 | P3: 47612057 | Q3: 9198.35 | R3: 7516562.4 | S3: 3562736.1 | T3: 47567.91 | U3: 33904.03 | V3: 3090.5 | W3: 743.26 | X3: 2479.17 | Y3: 2923574
A4: 198 | B4: 3 | C4: 2022 | D4: Australia | E4: 4609 | F4: 1.1806159e+08 | G4: 24214432 | H4: 20.51 | I4: 7.2 | J4: 11890.05 | K4: 2882.93 | L4: 1.1801067e+08 | M4: 1.1805165e+08 | N4: 50916.6 | O4: 1.1802493e+08 | P4: 1.1802184e+08 | Q4: 3088.14 | R4: 8500434.5 | S4: 15713998 | T4: 59022.66 | U4: 43541.15 | V4: 8239.45 | W4: 6019.91 | X4: 3712.6 | Y4: 3660463
A5: 268 | B5: 4 | C5: 2022 | D5: Australia | E5: 4805 | F5: 1.8415933e+08 | G5: 16997906 | H5: 9.23 | I5: 10.47 | J5: 7883.27 | K5: 18706.32 | L5: 1.8410723e+08 | M5: 1.8413483e+08 | N5: 52101.38 | O5: 1.8411493e+08 | P5: 1.8410712e+08 | Q5: 7807.86 | R5: 19281482 | S5: -2283575.7 | T5: 42862.86 | U5: 21925.53 | V5: 2950.2 | W5: 4750.74 | X5: 2684.35 | Y5: 1717702
A6: 338 | B6: 5 | C6: 2022 | D6: Australia | E6: 3311 | F6: 1.3885856e+08 | G6: 41227105 | H6: 29.69 | I6: 18.15 | J6: 1740.73 | K6: 10430.12 | L6: 138819081 | M6: 1.388434e+08 | N6: 39475.61 | O6: 1.3883506e+08 | P6: 1.3882324e+08 | Q6: 11811.75 | R6: 25202828 | S6: 16024277 | T6: 73537.9 | U6: 32538.36 | V6: 11630.58 | W6: 4344.14 | X6: 3855.66 | Y6: 2331397
A7: 408 | B7: 6 | C7: 2022 | D7: Australia | E7: 1362 | F7: 33027066 | G7: 3438117.6 | H7: 10.41 | I7: 15.22 | J7: 11900.93 | K7: 15760.63 | L7: 32991581 | M7: 33022492 | N7: 35485.26 | O7: 32997346 | P7: 32983066 | Q7: 14280.44 | R7: 5026719.4 | S7: -1588601.9 | T7: 74662.15 | U7: 48081.47 | V7: 2158.75 | W7: 3607.08 | X7: 2858.94 | Y7: 1014435
A8: 478 | B8: 7 | C8: 2022 | D8: Australia | E8: 4086 | F8: 2.0101784e+08 | G8: 20905855 | H8: 10.4 | I8: 14.36 | J8: 2189.8 | K8: 18752.26 | L8: 2.0098618e+08 | M8: 201000796 | N8: 31661.71 | O8: 2.0099432e+08 | P8: 2.0099133e+08 | Q8: 2986.35 | R8: 28866162 | S8: -7960306.5 | T8: 41704.05 | U8: 6131.71 | V8: 7432.8 | W8: 705.57 | X8: 1579.05 | Y8: 1167094
A9: 548 | B9: 8 | C9: 2022 | D9: Australia | E9: 6543 | F9: 1.8143513e+08 | G9: 40822904 | H9: 22.5 | I9: 7.52 | J9: 6758.69 | K9: 5938.98 | L9: 1.8141489e+08 | M9: 181428728 | N9: 20239.05 | O9: 181423481 | P9: 1.8141441e+08 | Q9: 9067.73 | R9: 13643922 | S9: 27178982 | T9: 23081.78 | U9: 6266.26 | V9: 6905.82 | W9: 1686.05 | X9: 1993.73 | Y9: 3777026
A10: 618 | B10: 9 | C10: 2022 | D10: Australia | E10: 4018 | F10: 2.0990668e+08 | G10: 48320519 | H10: 23.02 | I10: 14.48 | J10: 8893.67 | K10: 16223.11 | L10: 2.0986956e+08 | M10: 2.0989747e+08 | N10: 37126.24 | O10: 2.0987949e+08 | P10: 2.0987209e+08 | Q10: 7402.41 | R10: 30394488 | S10: 17926031 | T10: 71637.08 | U10: 19986.94 | V10: 9229.94 | W10: 705.54 | X10: 1687.53 | Y10: 2607803
A11: 688 | B11: 10 | C11: 2022 | D11: Australia | E11: 2795 | F11: 1.0747452e+08 | G11: 10167089 | H11: 9.46 | I11: 9.33 | J11: 1096.64 | K11: 4672.69 | L11: 1.0743996e+08 | M11: 107450156 | N11: 34562.06 | O11: 1.0745171e+08 | P11: 1.0744859e+08 | Q11: 3121.33 | R11: 10027372 | S11: 139716.87 | T11: 92118.41 | U11: 49861.87 | V11: 4471.35 | W11: 7283.99 | X11: 1799.98 | Y11: 1704710
A12: 758 | B12: 11 | C12: 2022 | D12: Australia | E12: 3824 | F12: 54957006 | G12: 5803459.8 | H12: 10.56 | I12: 18.04 | J12: 3863.67 | K12: 5005.4 | L12: 54907174 | M12: 54946930 | N12: 49832.11 | O12: 54916508 | P12: 54913979 | Q12: 2529.5 | R12: 9914243.9 | S12: -4110784 | T12: 49899.15 | U12: 8801.94 | V12: 7879.87 | W12: 1454.51 | X12: 4632.28 | Y12: 3696765
A13: 828 | B13: 12 | C13: 2022 | D13: Australia | E13: 3475 | F13: 1.0276419e+08 | G13: 25444414 | H13: 24.76 | I13: 9.53 | J13: 5199.16 | K13: 19670.82 | L13: 1.0271239e+08 | M13: 1.0273927e+08 | N13: 51799.69 | O13: 1.0271929e+08 | P13: 1.0271498e+08 | Q13: 4317.37 | R13: 9793427.4 | S13: 15650986 | T13: 32097.64 | U13: 7461.66 | V13: 2803.08 | W13: 4098.06 | X13: 3471.68 | Y13: 3388823
... A1051: 3450 | B1051: 50 | C1051: 2024 | D1051: USA | E1051: 6280 | F1051: 43547185 | G1051: 5395496.2 | H1051: 12.39 | I1051: 18.41 | J1051: 8967.53 | K1051: 2942.05 | L1051: 43524418 | M1051: 43532005 | N1051: 22766.15 | O1051: 43532410 | P1051: 43525338 | Q1051: 7072.21 | R1051: 8017036.7 | S1051: -2621540.5 | T1051: 78668.84 | U1051: 27153.58 | V1051: 1341.61 | W1051: 6650.06 | X1051: 4951.97 | Y1051: 4876154

Sheet Year_Summary
C3: Year-wise Summary (FY2022 - FY2024)
C4: Metric | D4: 2022 | E4: 2023 | F4: 2024 | G4: Total
C5: Units Sold | D5: =SUMIFS('TATA FINANCE'!$E$2:$E$1051,'TATA FINANCE'!$C$2:$C$1051,D$4) -> 1234585 | E5: =SUMIFS('TATA FINANCE'!$E$2:$E$1051,'TATA FINANCE'!$C$2:$C$1051,E$4) -> 1256786 | F5: =SUMIFS('TATA FINANCE'!$E$2:$E$1051,'TATA FINANCE'!$C$2:$C$1051,F$4) -> 1224670 | G5: =SUM(D5:F5) -> 3716041
C6: Net Revenue (USD) | D6: =SUMIFS('TATA FINANCE'!$L$2:$L$1051,'TATA FINANCE'!$C$2:$C$1051,D$4) -> 4.7237449e+10 | E6: =SUMIFS('TATA FINANCE'!$L$2:$L$1051,'TATA FINANCE'!$C$2:$C$1051,E$4) -> 4.7520172e+10 | F6: =SUMIFS('TATA FINANCE'!$L$2:$L$1051,'TATA FINANCE'!$C$2:$C$1051,F$4) -> 4.4838537e+10 | G6: =SUM(D6:F6) -> 1.3959616e+11
C7: Gross Margin (USD) | D7: =SUMIFS('TATA FINANCE'!$M$2:$M$1051,'TATA FINANCE'!$C$2:$C$1051,D$4) -> 4.7251355e+10 | E7: =SUMIFS('TATA FINANCE'!$M$2:$M$1051,'TATA FINANCE'!$C$2:$C$1051,E$4) -> 4.7534143e+10 | F7: =SUMIFS('TATA FINANCE'!$M$2:$M$1051,'TATA FINANCE'!$C$2:$C$1051,F$4) -> 4.4852312e+10 | G7: =SUM(D7:F7) -> 1.3963781e+11
C8: EBITDA (USD) | D8: =SUMIFS('TATA FINANCE'!$O$2:$O$1051,'TATA FINANCE'!$C$2:$C$1051,D$4) -> 4.7241328e+10 | E8: =SUMIFS('TATA FINANCE'!$O$2:$O$1051,'TATA FINANCE'!$C$2:$C$1051,E$4) -> 4.7523884e+10 | F8: =SUMIFS('TATA FINANCE'!$O$2:$O$1051,'TATA FINANCE'!$C$2:$C$1051,F$4) -> 4.48423e+10 | G8: =SUM(D8:F8) -> 1.3960751e+11
C9: EBIT (USD) | D9: =SUMIFS('TATA FINANCE'!$P$2:$P$1051,'TATA FINANCE'!$C$2:$C$1051,D$4) -> 4.7238422e+10 | E9: =SUMIFS('TATA FINANCE'!$P$2:$P$1051,'TATA FINANCE'!$C$2:$C$1051,E$4) -> 4.7521141e+10 | F9: =SUMIFS('TATA FINANCE'!$P$2:$P$1051,'TATA FINANCE'!$C$2:$C$1051,F$4) -> 4.4839454e+10 | G9: =SUM(D9:F9) -> 1.3959902e+11
C10: Net Profit (USD) | D10: =SUMIFS('TATA FINANCE'!$S$2:$S$1051,'TATA FINANCE'!$C$2:$C$1051,D$4) -> 1.9444014e+09 | E10: =SUMIFS('TATA FINANCE'!$S$2:$S$1051,'TATA FINANCE'!$C$2:$C$1051,E$4) -> 1.9884056e+09 | F10: =SUMIFS('TATA FINANCE'!$S$2:$S$1051,'TATA FINANCE'!$C$2:$C$1051,F$4) -> 2.2860848e+09 | G10: =SUM(D10:F10) -> 6.2188918e+09
C12: Ratios | D12: =D4 -> 2022 | E12: =E4 -> 2023 | F12: =F4 -> 2024 | G12: Overall
C13: Net Profit Margin (%) | D13: =IFERROR(D10/D6,0) -> 0.041162286 | E13: =IFERROR(E10/E6,0) -> 0.0418434 | F13: =IFERROR(F10/F6,0) -> 0.050984823 | G13: =IFERROR(G10/G6,0) -> 0.044549162
C14: Gross Margin (%) | D14: =IFERROR(D7/D6,0) -> 1.0002944 | E14: =IFERROR(E7/E6,0) -> 1.000294 | F14: =IFERROR(F7/F6,0) -> 1.0003072 | G14: =IFERROR(G7/G6,0) -> 1.0002984
C15: EBITDA Margin (%) | D15: =IFERROR(D8/D6,0) -> 1.0000821 | E15: =IFERROR(E8/E6,0) -> 1.0000781 | F15: =IFERROR(F8/F6,0) -> 1.0000839 | G15: =IFERROR(G8/G6,0) -> 1.0000813
C16: EBIT Margin (%) | D16: =IFERROR(D9/D6,0) -> 1.0000206 | E16: =IFERROR(E9/E6,0) -> 1.0000204 | F16: =IFERROR(F9/F6,0) -> 1.0000205 | G16: =IFERROR(G9/G6,0) -> 1.0000205
C17: Net Revenue Growth (YoY %) | D17: n/a | E17: =IFERROR(E6/D6-1,0) -> 0.0059851358 | F17: =IFERROR(F6/E6-1,0) -> -0.056431513
C18: Units Sold Growth (YoY %) | D18: n/a | E18: =IFERROR(E5/D5-1,0) -> 0.017982561 | F18: =IFERROR(F5/E5-1,0) -> -0.025554072
C19: Net Profit Growth (YoY %) | D19: n/a | E19: =IFERROR(E10/D10-1,0) -> 0.022631213 | F19: =IFERROR(F10/E10-1,0) -> 0.14970751
C21: Note: Gross Margin, EBITDA and EBIT are close to Net Revenue in the source data, so their margins are near 100%. Net Profit Margin is the main profitability measure.

Sheet Country_Summary
A1: Country-wise Summary (FY2022 - FY2024 combined)
A4: Country | B4: Units Sold | C4: Net Revenue (USD) | D4: Net Profit (USD) | E4: Net Profit Margin (%)
A5: Australia | B5: =SUMIFS('TATA FINANCE'!$E$2:$E$1051,'TATA FINANCE'!$D$2:$D$1051,$A5) -> 534068 | C5: =SUMIFS('TATA FINANCE'!$L$2:$L$1051,'TATA FINANCE'!$D$2:$D$1051,$A5) -> 2.0257881e+10 | D5: =SUMIFS('TATA FINANCE'!$S$2:$S$1051,'TATA FINANCE'!$D$2:$D$1051,$A5) -> 8.9646745e+08 | E5: =IFERROR(D5/C5,0) -> 0.044252774
A6: France | B6: =SUMIFS('TATA FINANCE'!$E$2:$E$1051,'TATA FINANCE'!$D$2:$D$1051,$A6) -> 497721 | C6: =SUMIFS('TATA FINANCE'!$L$2:$L$1051,'TATA FINANCE'!$D$2:$D$1051,$A6) -> 1.8316122e+10 | D6: =SUMIFS('TATA FINANCE'!$S$2:$S$1051,'TATA FINANCE'!$D$2:$D$1051,$A6) -> 8.8254557e+08 | E6: =IFERROR(D6/C6,0) -> 0.048184085
A7: Germany | B7: =SUMIFS('TATA FINANCE'!$E$2:$E$1051,'TATA FINANCE'!$D$2:$D$1051,$A7) -> 507928 | C7: =SUMIFS('TATA FINANCE'!$L$2:$L$1051,'TATA FINANCE'!$D$2:$D$1051,$A7) -> 1.9075346e+10 | D7: =SUMIFS('TATA FINANCE'!$S$2:$S$1051,'TATA FINANCE'!$D$2:$D$1051,$A7) -> 7.0767343e+08 | E7: =IFERROR(D7/C7,0) -> 0.037098851
A8: India | B8: =SUMIFS('TATA FINANCE'!$E$2:$E$1051,'TATA FINANCE'!$D$2:$D$1051,$A8) -> 559649 | C8: =SUMIFS('TATA FINANCE'!$L$2:$L$1051,'TATA FINANCE'!$D$2:$D$1051,$A8) -> 2.0910794e+10 | D8: =SUMIFS('TATA FINANCE'!$S$2:$S$1051,'TATA FINANCE'!$D$2:$D$1051,$A8) -> 8.2759216e+08 | E8: =IFERROR(D8/C8,0) -> 0.03957727
A9: Japan | B9: =SUMIFS('TATA FINANCE'!$E$2:$E$1051,'TATA FINANCE'!$D$2:$D$1051,$A9) -> 543175 | C9: =SUMIFS('TATA FINANCE'!$L$2:$L$1051,'TATA FINANCE'!$D$2:$D$1051,$A9) -> 2.0597508e+10 | D9: =SUMIFS('TATA FINANCE'!$S$2:$S$1051,'TATA FINANCE'!$D$2:$D$1051,$A9) -> 8.5857631e+08 | E9: =IFERROR(D9/C9,0) -> 0.041683504
A10: UK | B10: =SUMIFS('TATA FINANCE'!$E$2:$E$1051,'TATA FINANCE'!$D$2:$D$1051,$A10) -> 543974 | C10: =SUMIFS('TATA FINANCE'!$L$2:$L$1051,'TATA FINANCE'!$D$2:$D$1051,$A10) -> 2.035322e+10 | D10: =SUMIFS('TATA FINANCE'!$S$2:$S$1051,'TATA FINANCE'!$D$2:$D$1051,$A10) -> 1.1931846e+09 | E10: =IFERROR(D10/C10,0) -> 0.058623871
A11: USA | B11: =SUMIFS('TATA FINANCE'!$E$2:$E$1051,'TATA FINANCE'!$D$2:$D$1051,$A11) -> 529526 | C11: =SUMIFS('TATA FINANCE'!$L$2:$L$1051,'TATA FINANCE'!$D$2:$D$1051,$A11) -> 2.0085285e+10 | D11: =SUMIFS('TATA FINANCE'!$S$2:$S$1051,'TATA FINANCE'!$D$2:$D$1051,$A11) -> 8.5285234e+08 | E11: =IFERROR(D11/C11,0) -> 0.04246155
A12: Total | B12: =SUM(B5:B11) -> 3716041 | C12: =SUM(C5:C11) -> 1.3959616e+11 | D12: =SUM(D5:D11) -> 6.2188918e+09 | E12: =IFERROR(D12/C12,0) -> 0.044549162
A14: Net Profit (USD) by Country and Year
A15: Country | B15: 2022 | C15: 2023 | D15: 2024 | E15: Total
A16: Australia | B16: =SUMIFS('TATA FINANCE'!$S$2:$S$1051,'TATA FINANCE'!$D$2:$D$1051,$A16,'TATA FINANCE'!$C$2:$C$1051,B$15) -> 3.8482082e+08 | C16: =SUMIFS('TATA FINANCE'!$S$2:$S$1051,'TATA FINANCE'!$D$2:$D$1051,$A16,'TATA FINANCE'!$C$2:$C$1051,C$15) -> 2.9752764e+08 | D16: =SUMIFS('TATA FINANCE'!$S$2:$S$1051,'TATA FINANCE'!$D$2:$D$1051,$A16,'TATA FINANCE'!$C$2:$C$1051,D$15) -> 2.14119e+08 | E16: =SUM(B16:D16) -> 8.9646745e+08
A17: France | B17: =SUMIFS('TATA FINANCE'!$S$2:$S$1051,'TATA FINANCE'!$D$2:$D$1051,$A17,'TATA FINANCE'!$C$2:$C$1051,B$15) -> 3.8507845e+08 | C17: =SUMIFS('TATA FINANCE'!$S$2:$S$1051,'TATA FINANCE'!$D$2:$D$1051,$A17,'TATA FINANCE'!$C$2:$C$1051,C$15) -> 1.8857366e+08 | D17: =SUMIFS('TATA FINANCE'!$S$2:$S$1051,'TATA FINANCE'!$D$2:$D$1051,$A17,'TATA FINANCE'!$C$2:$C$1051,D$15) -> 3.0889345e+08 | E17: =SUM(B17:D17) -> 8.8254557e+08
A18: Germany | B18: =SUMIFS('TATA FINANCE'!$S$2:$S$1051,'TATA FINANCE'!$D$2:$D$1051,$A18,'TATA FINANCE'!$C$2:$C$1051,B$15) -> 2.0465015e+08 | C18: =SUMIFS('TATA FINANCE'!$S$2:$S$1051,'TATA FINANCE'!$D$2:$D$1051,$A18,'TATA FINANCE'!$C$2:$C$1051,C$15) -> 82969694 | D18: =SUMIFS('TATA FINANCE'!$S$2:$S$1051,'TATA FINANCE'!$D$2:$D$1051,$A18,'TATA FINANCE'!$C$2:$C$1051,D$15) -> 4.2005358e+08 | E18: =SUM(B18:D18) -> 7.0767343e+08
A19: India | B19: =SUMIFS('TATA FINANCE'!$S$2:$S$1051,'TATA FINANCE'!$D$2:$D$1051,$A19,'TATA FINANCE'!$C$2:$C$1051,B$15) -> 2.3406456e+08 | C19: =SUMIFS('TATA FINANCE'!$S$2:$S$1051,'TATA FINANCE'!$D$2:$D$1051,$A19,'TATA FINANCE'!$C$2:$C$1051,C$15) -> 2.859312e+08 | D19: =SUMIFS('TATA FINANCE'!$S$2:$S$1051,'TATA FINANCE'!$D$2:$D$1051,$A19,'TATA FINANCE'!$C$2:$C$1051,D$15) -> 3.075964e+08 | E19: =SUM(B19:D19) -> 8.2759216e+08
A20: Japan | B20: =SUMIFS('TATA FINANCE'!$S$2:$S$1051,'TATA FINANCE'!$D$2:$D$1051,$A20,'TATA FINANCE'!$C$2:$C$1051,B$15) -> 1.2435189e+08 | C20: =SUMIFS('TATA FINANCE'!$S$2:$S$1051,'TATA FINANCE'!$D$2:$D$1051,$A20,'TATA FINANCE'!$C$2:$C$1051,C$15) -> 3.8597388e+08 | D20: =SUMIFS('TATA FINANCE'!$S$2:$S$1051,'TATA FINANCE'!$D$2:$D$1051,$A20,'TATA FINANCE'!$C$2:$C$1051,D$15) -> 3.4825053e+08 | E20: =SUM(B20:D20) -> 8.5857631e+08
A21: UK | B21: =SUMIFS('TATA FINANCE'!$S$2:$S$1051,'TATA FINANCE'!$D$2:$D$1051,$A21,'TATA FINANCE'!$C$2:$C$1051,B$15) -> 3.4020463e+08 | C21: =SUMIFS('TATA FINANCE'!$S$2:$S$1051,'TATA FINANCE'!$D$2:$D$1051,$A21,'TATA FINANCE'!$C$2:$C$1051,C$15) -> 4.9026201e+08 | D21: =SUMIFS('TATA FINANCE'!$S$2:$S$1051,'TATA FINANCE'!$D$2:$D$1051,$A21,'TATA FINANCE'!$C$2:$C$1051,D$15) -> 3.6271792e+08 | E21: =SUM(B21:D21) -> 1.1931846e+09
A22: USA | B22: =SUMIFS('TATA FINANCE'!$S$2:$S$1051,'TATA FINANCE'!$D$2:$D$1051,$A22,'TATA FINANCE'!$C$2:$C$1051,B$15) -> 2.7123091e+08 | C22: =SUMIFS('TATA FINANCE'!$S$2:$S$1051,'TATA FINANCE'!$D$2:$D$1051,$A22,'TATA FINANCE'!$C$2:$C$1051,C$15) -> 2.5716749e+08 | D22: =SUMIFS('TATA FINANCE'!$S$2:$S$1051,'TATA FINANCE'!$D$2:$D$1051,$A22,'TATA FINANCE'!$C$2:$C$1051,D$15) -> 3.2445394e+08 | E22: =SUM(B22:D22) -> 8.5285234e+08
A23: Total | B23: =SUM(B16:B22) -> 1.9444014e+09 | C23: =SUM(C16:C22) -> 1.9884056e+09 | D23: =SUM(D16:D22) -> 2.2860848e+09 | E23: =SUM(E16:E22) -> 6.2188918e+09

Sheet Descriptive_Stats
B1: Descriptive Statistics (per record)
B4: Variable | C4: Count | D4: Mean | E4: Median | F4: Minimum | G4: Maximum | H4: Std. Deviation
B5: Units Sold | C5: =COUNT('TATA FINANCE'!$E$2:$E$1051) -> 1050 | D5: =AVERAGE('TATA FINANCE'!$E$2:$E$1051) -> 3539.0867 | E5: =MEDIAN('TATA FINANCE'!$E$2:$E$1051) -> 3557 | F5: =MIN('TATA FINANCE'!$E$2:$E$1051) -> 104 | G5: =MAX('TATA FINANCE'!$E$2:$E$1051) -> 6956 | H5: =STDEV('TATA FINANCE'!$E$2:$E$1051) -> 2023.8706
B6: Net Revenue (USD) | C6: =COUNT('TATA FINANCE'!$L$2:$L$1051) -> 1050 | D6: =AVERAGE('TATA FINANCE'!$L$2:$L$1051) -> 1.3294872e+08 | E6: =MEDIAN('TATA FINANCE'!$L$2:$L$1051) -> 1.0737458e+08 | F6: =MIN('TATA FINANCE'!$L$2:$L$1051) -> 976624.25 | G6: =MAX('TATA FINANCE'!$L$2:$L$1051) -> 4.7261297e+08 | H6: =STDEV('TATA FINANCE'!$L$2:$L$1051) -> 1.0664809e+08
B7: Net Profit (USD) | C7: =COUNT('TATA FINANCE'!$S$2:$S$1051) -> 1050 | D7: =AVERAGE('TATA FINANCE'!$S$2:$S$1051) -> 5922754.1 | E7: =MEDIAN('TATA FINANCE'!$S$2:$S$1051) -> 2753343.5 | F7: =MIN('TATA FINANCE'!$S$2:$S$1051) -> -54935399 | G7: =MAX('TATA FINANCE'!$S$2:$S$1051) -> 87270176 | H7: =STDEV('TATA FINANCE'!$S$2:$S$1051) -> 14412934
B8: Profit Margin (%) | C8: =COUNT('TATA FINANCE'!$H$2:$H$1051) -> 1050 | D8: =AVERAGE('TATA FINANCE'!$H$2:$H$1051) -> 17.239819 | E8: =MEDIAN('TATA FINANCE'!$H$2:$H$1051) -> 17.02 | F8: =MIN('TATA FINANCE'!$H$2:$H$1051) -> 5.01 | G8: =MAX('TATA FINANCE'!$H$2:$H$1051) -> 29.94 | H8: =STDEV('TATA FINANCE'!$H$2:$H$1051) -> 7.2490785
